{"StatID":2173053,"TeamID":5,"PlayerID":10007266,"SeasonType":1,"Season":2018,"Name":"Jake Junis","Team":"KC","Position":"SP","PositionCategory":"P","Started":30,"BattingOrder":null,"GlobalTeamID":10000005,"AverageDraftPosition":null,"Updated":"2018-12-31T03:19:03","Games":30,"FantasyPoints":143.1,"AtBats":2.3,"Runs":0.0,"Hits":0.0,"Singles":0.0,"Doubles":0.0,"Triples":0.0,"HomeRuns":0.0,"RunsBattedIn":0.0,"BattingAverage":0.0,"Outs":2.3,"Strikeouts":1.1,"Walks":0.0,"HitByPitch":0.0,"Sacrifices":0.0,"SacrificeFlies":0.0,"GroundIntoDoublePlay":0.0,"StolenBases":0.0,"CaughtStealing":0.0,"PitchesSeen":9.0,"OnBasePercentage":0.0,"SluggingPercentage":0.0,"OnBasePlusSlugging":0.0,"Errors":1.1,"Wins":10.1,"Losses":12.4,"Saves":0.0,"InningsPitchedDecimal":199.5,"TotalOutsPitched":598.4,"InningsPitchedFull":199.5,"InningsPitchedOuts":0.0,"EarnedRunAverage":4.9,"PitchingHits":205.1,"PitchingRuns":105.9,"PitchingEarnedRuns":96.9,"PitchingWalks":48.5,"PitchingStrikeouts":184.8,"PitchingHomeRuns":36.1,"PitchesThrown":3198.4,"PitchesThrownStrikes":2070.3,"WalksHitsPerInningsPitched":1.4,"PitchingBattingAverageAgainst":0.3,"GrandSlams":0.0,"FantasyPointsFanDuel":986.1,"FantasyPointsDraftKings":505.7,"FantasyPointsYahoo":571.4,"PlateAppearances":2.3,"TotalBases":0.0,"FlyOuts":0.0,"GroundOuts":0.0,"LineOuts":0.0,"PopOuts":0.0,"IntentionalWalks":0.0,"ReachedOnError":0.0,"BallsInPlay":1.1,"BattingAverageOnBallsInPlay":0.0,"WeightedOnBasePercentage":0.0,"PitchingSingles":134.1,"PitchingDoubles":30.4,"PitchingTriples":4.5,"PitchingGrandSlams":2.3,"PitchingHitByPitch":16.9,"PitchingSacrifices":3.4,"PitchingSacrificeFlies":9.0,"PitchingGroundIntoDoublePlay":12.4,"PitchingCompleteGames":1.1,"PitchingShutOuts":0.0,"PitchingNoHitters":0.0,"PitchingPerfectGames":0.0,"PitchingPlateAppearances":854.3,"PitchingTotalBases":352.8,"PitchingFlyOuts":105.9,"PitchingGroundOuts":154.4,"PitchingLineOuts":44.0,"PitchingPopOuts":32.7,"PitchingIntentionalWalks":1.1,"PitchingReachedOnError":6.8,"PitchingCatchersInterference":0.0,"PitchingBallsInPlay":564.6,"PitchingOnBasePercentage":0.4,"PitchingSluggingPercentage":0.5,"PitchingOnBasePlusSlugging":0.9,"PitchingStrikeoutsPerNineInnings":9.4,"PitchingWalksPerNineInnings":2.5,"PitchingBattingAverageOnBallsInPlay":0.3,"PitchingWeightedOnBasePercentage":0.4,"DoublePlays":0.0,"PitchingDoublePlays":14.7,"BattingOrderConfirmed":true,"IsolatedPower":0.0,"FieldingIndependentPitching":5.2,"PitchingQualityStarts":15.8,"PitchingInningStarted":null,"LeftOnBase":1.1,"PitchingHolds":0.0,"PitchingBlownSaves":0.0,"SubstituteBattingOrder":null,"SubstituteBattingOrderSequence":null,"FantasyPointsFantasyDraft":505.7}