{"player_info":{"copyRight":" Copyright 2019 MLB Advanced Media, L.P.  Use of any content on this page acknowledges agreement to the terms posted here http://gdx.mlb.com/components/copyright.txt  ","queryResults":{"created":"2019-03-25T22:37:02","totalSize":"1","row":{"birth_country":"USA","name_prefix":"","name_display_first_last":"Ben Zobrist","college":"Dallas Baptist","height_inches":"3","death_country":"","age":"37","name_display_first_last_html":"Ben Zobrist","gender":"M","height_feet":"6","pro_debut_date":"2006-08-01T00:00:00","death_date":"","primary_position":"4","birth_date":"1981-05-26T00:00:00","team_abbrev":"CHC","status":"Active","name_display_last_first_html":"Zobrist, Ben","throws":"R","death_city":"","primary_position_txt":"2B","high_school":"Eureka, IL","name_display_roster_html":"Zobrist","name_use":"Ben","player_id":"450314","status_date":"2018-04-28T00:00:00","primary_stat_type":"hitting","team_id":"112","active_sw":"Y","primary_sport_code":"mlb","birth_state":"IL","weight":"210","name_middle":"Thomas","name_display_roster":"Zobrist","end_date":"","jersey_number":"18","death_state":"","name_first":"Benjamin","bats":"S","team_code":"chn","birth_city":"Eureka","name_nick":"Zorilla","status_code":"A","name_matrilineal":"","team_name":"Chicago Cubs","name_display_last_first":"Zobrist, Ben","twitter_id":"@benzobrist18","name_title":"","file_code":"chc","name_last":"Zobrist","start_date":"2015-12-08T00:00:00","name_full":"Zobrist, Ben"}}}}