{"player_info":{"copyRight":" Copyright 2019 MLB Advanced Media, L.P.  Use of any content on this page acknowledges agreement to the terms posted here http://gdx.mlb.com/components/copyright.txt  ","queryResults":{"created":"2019-04-01T17:36:19","totalSize":"1","row":{"birth_country":"USA","name_prefix":"","name_display_first_last":"Mike Minor","college":"Vanderbilt","height_inches":"4","death_country":"","age":"31","name_display_first_last_html":"Mike Minor","gender":"M","height_feet":"6","pro_debut_date":"2010-08-09T00:00:00","death_date":"","primary_position":"1","birth_date":"1987-12-26T00:00:00","team_abbrev":"TEX","status":"Active","name_display_last_first_html":"Minor, Mike","throws":"L","death_city":"","primary_position_txt":"P","high_school":"Forrest, Chapel Hill, TN","name_display_roster_html":"Minor","name_use":"Mike","player_id":"501985","status_date":"2019-01-23T00:00:00","primary_stat_type":"pitching","team_id":"140","active_sw":"Y","primary_sport_code":"mlb","birth_state":"TN","weight":"210","name_middle":"David","name_display_roster":"Minor","end_date":"","jersey_number":"23","death_state":"","name_first":"Michael","bats":"R","team_code":"tex","birth_city":"Chapel Hill","name_nick":"Spykezylla","status_code":"A","name_matrilineal":"","team_name":"Texas Rangers","name_display_last_first":"Minor, Mike","twitter_id":"@MikeMinor36","name_title":"","file_code":"tex","name_last":"Minor","start_date":"2017-12-06T00:00:00","name_full":"Minor, Mike"}}}}