{"sport_pitching_tm":{"copyRight":" Copyright 2019 MLB Advanced Media, L.P.  Use of any content on this page acknowledges agreement to the terms posted here http://gdx.mlb.com/components/copyright.txt  ","queryResults":{"created":"2019-04-01T17:31:21","totalSize":"1","row":{"gidp":"9","h9":"10.58","np":"1447","tr":"1","gf":"5","sport_code":"mlb","bqs":"5","hgnd":"24","sho":"0","bq":"14","gidp_opp":"47","bk":"1","kbb":"1.50","sport_id":"1","hr9":"1.46","sv":"0","slg":".502","bb":"44","whip":"1.77","avg":".297","ops":".894","team_full":"Boston Red Sox","db":"22","league_full":"American League","team_abbrev":"BOS","hfly":"18","so":"66","tbf":"344","bb9":"5.35","league_id":"103","wp":"4","team_seq":"1","hpop":"0","league":"AL","hb":"4","cs":"3","pgs":"131.5","season":"2018","sb":"2","go_ao":"0.83","ppa":"4.21","cg":"0","player_id":"519141","gs":"11","ibb":"1","team_id":"111","pk":"1","go":"65","hr":"12","irs":"0","wpct":".250","era":"6.08","babip":".344","end_date":"2018-10-28T00:00:00","rs9":"4.62","qs":"2","league_short":"American","g":"26","ir":"1","hld":"2","k9":"8.03","sport":"MLB","team_short":"Boston","l":"6","svo":"0","h":"87","ip":"74.0","obp":".392","w":"2","hldr":"45","ao":"78","s":"877","r":"53","spct":"60.6","pip":"19.6","ab":"293","er":"50"}}}}