{"player_info":{"copyRight":" Copyright 2019 MLB Advanced Media, L.P.  Use of any content on this page acknowledges agreement to the terms posted here http://gdx.mlb.com/components/copyright.txt  ","queryResults":{"created":"2019-04-01T17:36:19","totalSize":"1","row":{"birth_country":"Venezuela","name_prefix":"","name_display_first_last":"German Marquez","college":"","height_inches":"1","death_country":"","age":"24","name_display_first_last_html":"German Márquez","gender":"M","height_feet":"6","pro_debut_date":"2016-09-08T00:00:00","death_date":"","primary_position":"1","birth_date":"1995-02-22T00:00:00","team_abbrev":"COL","status":"Active","name_display_last_first_html":"Márquez, German","throws":"R","death_city":"","primary_position_txt":"P","high_school":"","name_display_roster_html":"Márquez","name_use":"German","player_id":"608566","status_date":"2018-10-04T00:00:00","primary_stat_type":"pitching","team_id":"115","active_sw":"Y","primary_sport_code":"mlb","birth_state":"","weight":"225","name_middle":"Andres","name_display_roster":"Marquez","end_date":"","jersey_number":"48","death_state":"","name_first":"German","bats":"R","team_code":"col","birth_city":"San Felix","name_nick":"Marquee","status_code":"A","name_matrilineal":"","team_name":"Colorado Rockies","name_display_last_first":"Marquez, German","twitter_id":"","name_title":"","file_code":"col","name_last":"Marquez","start_date":"2016-01-28T00:00:00","name_full":"Marquez, German"}}}}